cloudscale/__init__.py
cloudscale/error.py
cloudscale/http.py
cloudscale/log.py
cloudscale/version.py
cloudscale/lib/__init__.py
cloudscale/lib/custom_image.py
cloudscale/lib/flavor.py
cloudscale/lib/floating_ip.py
cloudscale/lib/image.py
cloudscale/lib/network.py
cloudscale/lib/objects_user.py
cloudscale/lib/region.py
cloudscale/lib/server.py
cloudscale/lib/server_group.py
cloudscale/lib/subnet.py
cloudscale/lib/volume.py
cloudscale_sdk-0.7.0.dist-info/LICENSE
cloudscale_sdk-0.7.0.dist-info/METADATA
cloudscale_sdk-0.7.0.dist-info/WHEEL
cloudscale_sdk-0.7.0.dist-info/top_level.txt
cloudscale_sdk-0.7.0.dist-info/RECORD
