Metadata-Version: 2.1
Name: cloudscale-sdk
Version: 0.7.0
Summary: A library and SDK for cloudscale.ch
Home-page: https://github.com/cloudscale-ch/cloudscale-python-sdk
Author: René Moser
Author-email: mail@renemoser.net
License: MIT
Classifier: Intended Audience :: Developers
Classifier: Development Status :: 4 - Beta
Classifier: Programming Language :: Python :: 3
Classifier: License :: OSI Approved :: MIT License
Classifier: Operating System :: OS Independent
Classifier: Environment :: Console
Requires-Python: >=3.6
License-File: LICENSE
Requires-Dist: requests
Requires-Dist: xdg
Provides-Extra: highlight
Requires-Dist: pygments ; extra == 'highlight'
